patalynn/__init__.py
patalynn/__main__.py
patalynn/core/__init__.py
patalynn/core/gui.py
patalynn/manager/__init__.py
patalynn/manager/apple.py
patalynn-0.0.2.dist-info/LICENCE
patalynn-0.0.2.dist-info/METADATA
patalynn-0.0.2.dist-info/WHEEL
patalynn-0.0.2.dist-info/entry_points.txt
patalynn-0.0.2.dist-info/top_level.txt
patalynn-0.0.2.dist-info/RECORD
