Metadata-Version: 2.1
Name: patalynn
Version: 0.0.2
Summary: TODO
Author-email: Arsenic Vapor <guy99992@gmail.com>
Project-URL: Homepage, https://github.com/meemkoo/patalynn/
Project-URL: Issues, https://github.com/meemkoo/patalynn/issues
Classifier: Programming Language :: Python :: 3
Classifier: License :: OSI Approved :: GNU General Public License v3 (GPLv3)
Classifier: Operating System :: Microsoft :: Windows
Classifier: Topic :: Multimedia :: Graphics :: Viewers
Classifier: Topic :: Multimedia :: Video :: Display
Classifier: Intended Audience :: End Users/Desktop
Classifier: Intended Audience :: Developers
Classifier: Framework :: AsyncIO
Classifier: Development Status :: 2 - Pre-Alpha
Classifier: Environment :: Win32 (MS Windows)
Requires-Python: >=3.12
License-File: LICENCE
Requires-Dist: python-vlc>=3.0.21203
